{
    "Victor E Flores": {
        "7016": 267.0,
        "7017": 170.0,
        "7018": 178.0,
        "7019": 274.0,
        "7021": 244.0,
        "7022": 216.0,
        "7023": 251.0,
        "7024": 227.0,
        "7025": 220.0,
        "7026": 104.0,
        "7027": 208.0,
        "7028": 199.0,
        "7029": 236.0,
        "7031": 240.0,
        "7032": 180.0,
        "7033": 155.0,
        "7034": 169.0,
        "7035": 288.0,
        "7036": 219.0,
        "7037": 222.0,
        "7038": 167.0,
        "7051": 166.0,
        "7052": 253.0,
        "7053": 139.0,
        "7054": 292.0,
        "7055": 175.0,
        "7056": 145.0,
        "7645": 236.0,
        "9902": 0.0,
        "9903": 0.0,
        "9904": 0.0
    },
    "Dana Lang": {
        "7016": 95.0,
        "7017": 133.0,
        "7018": 111.0,
        "7019": 182.0,
        "7021": 227.0,
        "7022": 161.0,
        "7023": 85.0,
        "7024": 114.0,
        "7025": 148.0,
        "7026": 62.0,
        "7027": 122.0,
        "7028": 235.0,
        "7029": 149.0,
        "7031": 123.0,
        "7032": 91.0,
        "7033": 78.0,
        "7034": 81.0,
        "7035": 189.0,
        "7036": 191.0,
        "7037": 207.0,
        "7038": 116.0,
        "7051": 91.0,
        "7052": 262.0,
        "7053": 179.0,
        "7054": 199.0,
        "7055": 89.0,
        "7056": 117.0,
        "7645": 147.0,
        "9902": 0.0,
        "9903": 0.0,
        "9904": 0.0
    },
    "votes_cast": {
        "7016": 362.0,
        "7017": 303.0,
        "7018": 289.0,
        "7019": 456.0,
        "7021": 471.0,
        "7022": 377.0,
        "7023": 336.0,
        "7024": 341.0,
        "7025": 368.0,
        "7026": 166.0,
        "7027": 330.0,
        "7028": 434.0,
        "7029": 385.0,
        "7031": 363.0,
        "7032": 271.0,
        "7033": 233.0,
        "7034": 250.0,
        "7035": 477.0,
        "7036": 410.0,
        "7037": 429.0,
        "7038": 283.0,
        "7051": 257.0,
        "7052": 515.0,
        "7053": 318.0,
        "7054": 491.0,
        "7055": 264.0,
        "7056": 262.0,
        "7645": 383.0,
        "9902": 0.0,
        "9903": 0.0,
        "9904": 0.0
    }
}